czds/__init__.py
czds/__main__.py
czds/base.py
czds/configuration.py
czds/connector.py
czds/czds.py
czds/exceptions.py
czds/logger.py
czds/models.py
czds/py.typed
czds-0.1.4.dist-info/LICENSE.md
czds-0.1.4.dist-info/METADATA
czds-0.1.4.dist-info/WHEEL
czds-0.1.4.dist-info/entry_points.txt
czds-0.1.4.dist-info/RECORD
