Metadata-Version: 2.1
Name: czds
Version: 0.1.4
Summary: CZDS
Home-page: https://github.com/MSAdministrator/czds
License: MIT
Keywords: ICAAN,CZDS,DNS,Security
Author: Josh Rickard
Author-email: rickardja@live.com
Maintainer: Josh Rickard
Maintainer-email: rickardja@live.com
Requires-Python: >=3.10,<4.0
Classifier: Development Status :: 3 - Alpha
Classifier: License :: OSI Approved :: MIT License
Classifier: Programming Language :: Python :: 3
Classifier: Programming Language :: Python :: 3.10
Classifier: Programming Language :: Python :: 3.11
Requires-Dist: attrs (>=25.3.0,<26.0.0)
Requires-Dist: click (>=8.0.1)
Requires-Dist: fire (>=0.7.0,<0.8.0)
Requires-Dist: legacy-cgi (>=2.6.3,<3.0.0)
Requires-Dist: pre-commit (>=4.2.0,<5.0.0)
Requires-Dist: prompt-toolkit (>=3.0.36,<4.0.0)
Requires-Dist: pytest (>=8.4.1,<9.0.0)
Requires-Dist: pyyaml (>=6.0,<7.0)
Requires-Dist: requests (>=2.28.2,<3.0.0)
Requires-Dist: rich (>=13.3.1,<14.0.0)
Project-URL: Changelog, https://github.com/MSAdministrator/czds/releases
Project-URL: Repository, https://github.com/MSAdministrator/czds
